{
  "type": "class",
  "name": "MinecartFurnace",
  "qualified_name": "net.minecraft.world.entity.vehicle.MinecartFurnace",
  "package": "net.minecraft.world.entity.vehicle",
  "modifiers": [
    "public",
    "class"
  ],
  "annotations": [],
  "description": "",
  "inheritance": {
    "extends": null,
    "implements": [
      "CommandSource",
      "SyncedDataHolder",
      "EntityAccess",
      "Nameable",
      "ScoreHolder",
      "IAttachmentHolder",
      "IAbstractMinecartExtension",
      "IEntityExtension",
      "INBTSerializable",
      "CompoundTag"
    ],
    "inheritance_tree": [
      "java.lang.Object",
      "net.neoforged.neoforge.attachment.AttachmentHolder",
      "net.minecraft.world.entity.Entity",
      "net.minecraft.world.entity.vehicle.VehicleEntity",
      "net.minecraft.world.entity.vehicle.AbstractMinecart"
    ]
  },
  "nested_classes": [],
  "fields": [
    {
      "name": "DATA_ID_FUEL",
      "modifiers": [
        "private",
        "static",
        "final"
      ],
      "annotations": [],
      "type": "EntityDataAccessor < Boolean >",
      "value": null,
      "description": "",
      "deprecated": false
    },
    {
      "name": "fuel",
      "modifiers": [
        "private"
      ],
      "annotations": [],
      "type": "int",
      "value": null,
      "description": "",
      "deprecated": false
    },
    {
      "name": "xPush",
      "modifiers": [
        "public"
      ],
      "annotations": [],
      "type": "double",
      "value": null,
      "description": "",
      "deprecated": false
    },
    {
      "name": "zPush",
      "modifiers": [
        "public"
      ],
      "annotations": [],
      "type": "double",
      "value": null,
      "description": "",
      "deprecated": false
    },
    {
      "name": "INGREDIENT",
      "modifiers": [
        "private",
        "static",
        "final"
      ],
      "annotations": [],
      "type": "Ingredient",
      "value": null,
      "description": "",
      "deprecated": false
    }
  ],
  "constructors": [
    {
      "name": "MinecartFurnace",
      "modifiers": [
        "public"
      ],
      "annotations": [],
      "parameters": [
        {
          "name": "p_38552_",
          "type": "EntityType <? extends MinecartFurnace >",
          "annotations": []
        },
        {
          "name": "p_38553_",
          "type": "Level",
          "annotations": []
        }
      ],
      "exceptions": [],
      "description": "",
      "deprecated": false
    },
    {
      "name": "MinecartFurnace",
      "modifiers": [
        "public"
      ],
      "annotations": [],
      "parameters": [
        {
          "name": "p_38555_",
          "type": "Level",
          "annotations": []
        },
        {
          "name": "p_38556_",
          "type": "double",
          "annotations": []
        },
        {
          "name": "p_38557_",
          "type": "double",
          "annotations": []
        },
        {
          "name": "p_38558_",
          "type": "double",
          "annotations": []
        }
      ],
      "exceptions": [],
      "description": "",
      "deprecated": false
    }
  ],
  "methods": [
    {
      "name": "getMinecartType",
      "modifiers": [
        "public"
      ],
      "annotations": [],
      "return_type": "AbstractMinecart.Type",
      "parameters": [],
      "exceptions": [],
      "description": "",
      "overrides": null,
      "since": null,
      "deprecated": false
    },
    {
      "name": "defineSynchedData",
      "modifiers": [
        "protected"
      ],
      "annotations": [],
      "return_type": "void",
      "parameters": [
        {
          "name": "p_326389_",
          "type": "SynchedEntityData.Builder",
          "annotations": []
        }
      ],
      "exceptions": [],
      "description": "",
      "overrides": "defineSynchedData in class AbstractMinecart",
      "since": null,
      "deprecated": false
    },
    {
      "name": "tick",
      "modifiers": [
        "public"
      ],
      "annotations": [],
      "return_type": "void",
      "parameters": [],
      "exceptions": [],
      "description": "",
      "overrides": "tick in class AbstractMinecart",
      "since": null,
      "deprecated": false
    },
    {
      "name": "getMaxSpeed",
      "modifiers": [
        "protected"
      ],
      "annotations": [],
      "return_type": "double",
      "parameters": [],
      "exceptions": [],
      "description": "",
      "overrides": "getMaxSpeed in class AbstractMinecart",
      "since": null,
      "deprecated": false
    },
    {
      "name": "getDropItem",
      "modifiers": [
        "protected"
      ],
      "annotations": [],
      "return_type": "Item",
      "parameters": [],
      "exceptions": [],
      "description": "",
      "overrides": null,
      "since": null,
      "deprecated": false
    },
    {
      "name": "moveAlongTrack",
      "modifiers": [
        "protected"
      ],
      "annotations": [],
      "return_type": "void",
      "parameters": [
        {
          "name": "p_38569_",
          "type": "BlockPos",
          "annotations": []
        },
        {
          "name": "p_38570_",
          "type": "BlockState",
          "annotations": []
        }
      ],
      "exceptions": [],
      "description": "",
      "overrides": "moveAlongTrack in class AbstractMinecart",
      "since": null,
      "deprecated": false
    },
    {
      "name": "applyNaturalSlowdown",
      "modifiers": [
        "protected"
      ],
      "annotations": [],
      "return_type": "void",
      "parameters": [],
      "exceptions": [],
      "description": "",
      "overrides": "applyNaturalSlowdown in class AbstractMinecart",
      "since": null,
      "deprecated": false
    },
    {
      "name": "interact",
      "modifiers": [
        "public"
      ],
      "annotations": [],
      "return_type": "InteractionResult",
      "parameters": [
        {
          "name": "p_38562_",
          "type": "Player",
          "annotations": []
        },
        {
          "name": "p_38563_",
          "type": "InteractionHand",
          "annotations": []
        }
      ],
      "exceptions": [],
      "description": "",
      "overrides": "interact in class Entity",
      "since": null,
      "deprecated": false
    },
    {
      "name": "getMaxCartSpeedOnRail",
      "modifiers": [
        "public"
      ],
      "annotations": [],
      "return_type": "float",
      "parameters": [],
      "exceptions": [],
      "description": "Description copied from interface: IAbstractMinecartExtension",
      "overrides": null,
      "since": null,
      "deprecated": false
    },
    {
      "name": "addAdditionalSaveData",
      "modifiers": [
        "protected"
      ],
      "annotations": [],
      "return_type": "void",
      "parameters": [
        {
          "name": "p_38567_",
          "type": "CompoundTag",
          "annotations": []
        }
      ],
      "exceptions": [],
      "description": "",
      "overrides": "addAdditionalSaveData in class AbstractMinecart",
      "since": null,
      "deprecated": false
    },
    {
      "name": "readAdditionalSaveData",
      "modifiers": [
        "protected"
      ],
      "annotations": [],
      "return_type": "void",
      "parameters": [
        {
          "name": "p_38565_",
          "type": "CompoundTag",
          "annotations": []
        }
      ],
      "exceptions": [],
      "description": "",
      "overrides": "readAdditionalSaveData in class AbstractMinecart",
      "since": null,
      "deprecated": false
    },
    {
      "name": "hasFuel",
      "modifiers": [
        "protected"
      ],
      "annotations": [],
      "return_type": "boolean",
      "parameters": [],
      "exceptions": [],
      "description": "",
      "overrides": null,
      "since": null,
      "deprecated": false
    },
    {
      "name": "setHasFuel",
      "modifiers": [
        "protected"
      ],
      "annotations": [],
      "return_type": "void",
      "parameters": [
        {
          "name": "p_38577_",
          "type": "boolean",
          "annotations": []
        }
      ],
      "exceptions": [],
      "description": "",
      "overrides": null,
      "since": null,
      "deprecated": false
    },
    {
      "name": "getDefaultDisplayBlockState",
      "modifiers": [
        "public"
      ],
      "annotations": [],
      "return_type": "BlockState",
      "parameters": [],
      "exceptions": [],
      "description": "",
      "overrides": "getDefaultDisplayBlockState in class AbstractMinecart",
      "since": null,
      "deprecated": false
    }
  ],
  "enum_constants": [],
  "since": null,
  "deprecated": false,
  "source_file": "1.21.x-neoforge/net/minecraft/world/entity/vehicle/MinecartFurnace.html"
}