{
  "type": "class",
  "name": "DiggerItem",
  "qualified_name": "net.minecraft.world.item.DiggerItem",
  "package": "net.minecraft.world.item",
  "modifiers": [
    "public",
    "class"
  ],
  "annotations": [],
  "description": "",
  "inheritance": {
    "extends": null,
    "implements": [],
    "inheritance_tree": [
      "java.lang.Object",
      "net.minecraft.world.item.Item",
      "net.minecraft.world.item.TieredItem"
    ]
  },
  "nested_classes": [],
  "fields": [
    {
      "name": "blocks",
      "modifiers": [
        "private",
        "final"
      ],
      "type": "TagKey < Block >",
      "description": "",
      "deprecated": false
    },
    {
      "name": "speed",
      "modifiers": [
        "protected",
        "final"
      ],
      "type": "float",
      "description": "",
      "deprecated": false
    },
    {
      "name": "attackDamageBaseline",
      "modifiers": [
        "private",
        "final"
      ],
      "type": "float",
      "description": "",
      "deprecated": false
    },
    {
      "name": "defaultModifiers",
      "modifiers": [
        "private",
        "final"
      ],
      "type": "com.google.common.collect.Multimap< Attribute , AttributeModifier >",
      "description": "",
      "deprecated": false
    }
  ],
  "constructors": [
    {
      "name": "DiggerItem",
      "modifiers": [
        "public"
      ],
      "parameters": [
        {
          "name": "p_204108_",
          "type": "float",
          "annotations": []
        },
        {
          "name": "p_204109_",
          "type": "float",
          "annotations": []
        },
        {
          "name": "p_204110_",
          "type": "Tier",
          "annotations": []
        },
        {
          "name": "p_204111_",
          "type": "TagKey < Block >",
          "annotations": []
        },
        {
          "name": "p_204112_",
          "type": "Item.Properties",
          "annotations": []
        }
      ],
      "description": "",
      "deprecated": false
    }
  ],
  "methods": [
    {
      "name": "getDestroySpeed",
      "modifiers": [
        "public"
      ],
      "return_type": "float",
      "parameters": [
        {
          "name": "p_41004_",
          "type": "ItemStack",
          "annotations": []
        },
        {
          "name": "p_41005_",
          "type": "BlockState",
          "annotations": []
        }
      ],
      "description": "",
      "deprecated": false
    },
    {
      "name": "hurtEnemy",
      "modifiers": [
        "public"
      ],
      "return_type": "boolean",
      "parameters": [
        {
          "name": "p_40994_",
          "type": "ItemStack",
          "annotations": []
        },
        {
          "name": "p_40995_",
          "type": "LivingEntity",
          "annotations": []
        },
        {
          "name": "p_40996_",
          "type": "LivingEntity",
          "annotations": []
        }
      ],
      "description": "",
      "deprecated": false
    },
    {
      "name": "mineBlock",
      "modifiers": [
        "public"
      ],
      "return_type": "boolean",
      "parameters": [
        {
          "name": "p_40998_",
          "type": "ItemStack",
          "annotations": []
        },
        {
          "name": "p_40999_",
          "type": "Level",
          "annotations": []
        },
        {
          "name": "p_41000_",
          "type": "BlockState",
          "annotations": []
        },
        {
          "name": "p_41001_",
          "type": "BlockPos",
          "annotations": []
        },
        {
          "name": "p_41002_",
          "type": "LivingEntity",
          "annotations": []
        }
      ],
      "description": "",
      "deprecated": false
    },
    {
      "name": "getDefaultAttributeModifiers",
      "modifiers": [
        "public"
      ],
      "return_type": "com.google.common.collect.Multimap< Attribute , AttributeModifier >",
      "parameters": [
        {
          "name": "p_40990_",
          "type": "EquipmentSlot",
          "annotations": []
        }
      ],
      "description": "",
      "deprecated": false
    },
    {
      "name": "getAttackDamage",
      "modifiers": [
        "public"
      ],
      "return_type": "float",
      "parameters": [],
      "description": "",
      "deprecated": false
    },
    {
      "name": "isCorrectToolForDrops",
      "modifiers": [
        "public"
      ],
      "return_type": "boolean",
      "parameters": [
        {
          "name": "p_150816_",
          "type": "BlockState",
          "annotations": []
        }
      ],
      "description": "",
      "deprecated": false
    },
    {
      "name": "isCorrectToolForDrops",
      "modifiers": [
        "public"
      ],
      "return_type": "boolean",
      "parameters": [
        {
          "name": "stack",
          "type": "ItemStack",
          "annotations": []
        },
        {
          "name": "state",
          "type": "BlockState",
          "annotations": []
        }
      ],
      "description": "Description copied from interface: IForgeItem",
      "deprecated": false
    }
  ],
  "enum_constants": [],
  "since": null,
  "deprecated": false,
  "source_file": "Frameworks/1.19.3/net/minecraft/world/item/DiggerItem.html"
}