{
  "type": "class",
  "name": "BuiltInMetadata",
  "qualified_name": "net.minecraft.server.packs.BuiltInMetadata",
  "package": "net.minecraft.server.packs",
  "modifiers": [
    "public",
    "class"
  ],
  "annotations": [],
  "description": "",
  "inheritance": {
    "extends": null,
    "implements": [],
    "inheritance_tree": [
      "java.lang.Object"
    ]
  },
  "nested_classes": [],
  "fields": [
    {
      "name": "EMPTY",
      "modifiers": [
        "private",
        "static",
        "final"
      ],
      "type": "BuiltInMetadata",
      "description": "",
      "deprecated": false
    },
    {
      "name": "values",
      "modifiers": [
        "private",
        "final"
      ],
      "type": "Map < MetadataSectionSerializer <?>, ?>",
      "description": "",
      "deprecated": false
    }
  ],
  "constructors": [
    {
      "name": "BuiltInMetadata",
      "modifiers": [
        "private"
      ],
      "parameters": [
        {
          "name": "p_251588_",
          "type": "Map < MetadataSectionSerializer <?>, ?>",
          "annotations": []
        }
      ],
      "description": "",
      "deprecated": false
    }
  ],
  "methods": [
    {
      "name": "get",
      "modifiers": [
        "public"
      ],
      "return_type": "T",
      "parameters": [
        {
          "name": "p_251597_",
          "type": "MetadataSectionSerializer <T>",
          "annotations": []
        }
      ],
      "description": "",
      "deprecated": false
    },
    {
      "name": "of",
      "modifiers": [
        "public",
        "static"
      ],
      "return_type": "BuiltInMetadata",
      "parameters": [],
      "description": "",
      "deprecated": false
    },
    {
      "name": "of",
      "modifiers": [
        "public",
        "static"
      ],
      "return_type": "BuiltInMetadata",
      "parameters": [
        {
          "name": "p_248992_",
          "type": "MetadataSectionSerializer <T>",
          "annotations": []
        },
        {
          "name": "p_249997_",
          "type": "T",
          "annotations": []
        }
      ],
      "description": "",
      "deprecated": false
    },
    {
      "name": "of",
      "modifiers": [
        "public",
        "static"
      ],
      "return_type": "BuiltInMetadata",
      "parameters": [
        {
          "name": "p_252035_",
          "type": "MetadataSectionSerializer <T1>",
          "annotations": []
        },
        {
          "name": "p_252174_",
          "type": "T1",
          "annotations": []
        },
        {
          "name": "p_249734_",
          "type": "MetadataSectionSerializer <T2>",
          "annotations": []
        },
        {
          "name": "p_250020_",
          "type": "T2",
          "annotations": []
        }
      ],
      "description": "",
      "deprecated": false
    }
  ],
  "enum_constants": [],
  "since": null,
  "deprecated": false,
  "source_file": "Frameworks/1.20.3/net/minecraft/server/packs/BuiltInMetadata.html"
}