{
  "type": "class",
  "name": "PoolElementStructurePiece",
  "qualified_name": "net.minecraft.world.level.levelgen.structure.PoolElementStructurePiece",
  "package": "net.minecraft.world.level.levelgen.structure",
  "modifiers": [
    "public",
    "class"
  ],
  "annotations": [],
  "description": "",
  "inheritance": {
    "extends": null,
    "implements": [],
    "inheritance_tree": [
      "java.lang.Object",
      "net.minecraft.world.level.levelgen.structure.StructurePiece"
    ]
  },
  "nested_classes": [],
  "fields": [
    {
      "name": "LOGGER",
      "modifiers": [
        "private",
        "static",
        "final"
      ],
      "type": "org.slf4j.Logger",
      "description": "",
      "deprecated": false
    },
    {
      "name": "element",
      "modifiers": [
        "protected",
        "final"
      ],
      "type": "StructurePoolElement",
      "description": "",
      "deprecated": false
    },
    {
      "name": "position",
      "modifiers": [
        "protected"
      ],
      "type": "BlockPos",
      "description": "",
      "deprecated": false
    },
    {
      "name": "groundLevelDelta",
      "modifiers": [
        "private",
        "final"
      ],
      "type": "int",
      "description": "",
      "deprecated": false
    },
    {
      "name": "rotation",
      "modifiers": [
        "protected",
        "final"
      ],
      "type": "Rotation",
      "description": "",
      "deprecated": false
    },
    {
      "name": "junctions",
      "modifiers": [
        "private",
        "final"
      ],
      "type": "List < JigsawJunction >",
      "description": "",
      "deprecated": false
    },
    {
      "name": "structureTemplateManager",
      "modifiers": [
        "private",
        "final"
      ],
      "type": "StructureTemplateManager",
      "description": "",
      "deprecated": false
    }
  ],
  "constructors": [
    {
      "name": "PoolElementStructurePiece",
      "modifiers": [
        "public"
      ],
      "parameters": [
        {
          "name": "p_226495_",
          "type": "StructureTemplateManager",
          "annotations": []
        },
        {
          "name": "p_226496_",
          "type": "StructurePoolElement",
          "annotations": []
        },
        {
          "name": "p_226497_",
          "type": "BlockPos",
          "annotations": []
        },
        {
          "name": "p_226498_",
          "type": "int",
          "annotations": []
        },
        {
          "name": "p_226499_",
          "type": "Rotation",
          "annotations": []
        },
        {
          "name": "p_226500_",
          "type": "BoundingBox",
          "annotations": []
        }
      ],
      "description": "",
      "deprecated": false
    },
    {
      "name": "PoolElementStructurePiece",
      "modifiers": [
        "public"
      ],
      "parameters": [
        {
          "name": "p_192406_",
          "type": "StructurePieceSerializationContext",
          "annotations": []
        },
        {
          "name": "p_192407_",
          "type": "CompoundTag",
          "annotations": []
        }
      ],
      "description": "",
      "deprecated": false
    }
  ],
  "methods": [
    {
      "name": "addAdditionalSaveData",
      "modifiers": [
        "protected"
      ],
      "return_type": "void",
      "parameters": [
        {
          "name": "p_192425_",
          "type": "StructurePieceSerializationContext",
          "annotations": []
        },
        {
          "name": "p_192426_",
          "type": "CompoundTag",
          "annotations": []
        }
      ],
      "description": "",
      "deprecated": false
    },
    {
      "name": "postProcess",
      "modifiers": [
        "public"
      ],
      "return_type": "void",
      "parameters": [
        {
          "name": "p_226502_",
          "type": "WorldGenLevel",
          "annotations": []
        },
        {
          "name": "p_226503_",
          "type": "StructureManager",
          "annotations": []
        },
        {
          "name": "p_226504_",
          "type": "ChunkGenerator",
          "annotations": []
        },
        {
          "name": "p_226505_",
          "type": "RandomSource",
          "annotations": []
        },
        {
          "name": "p_226506_",
          "type": "BoundingBox",
          "annotations": []
        },
        {
          "name": "p_226507_",
          "type": "ChunkPos",
          "annotations": []
        },
        {
          "name": "p_226508_",
          "type": "BlockPos",
          "annotations": []
        }
      ],
      "description": "",
      "deprecated": false
    },
    {
      "name": "place",
      "modifiers": [
        "public"
      ],
      "return_type": "void",
      "parameters": [
        {
          "name": "p_226510_",
          "type": "WorldGenLevel",
          "annotations": []
        },
        {
          "name": "p_226511_",
          "type": "StructureManager",
          "annotations": []
        },
        {
          "name": "p_226512_",
          "type": "ChunkGenerator",
          "annotations": []
        },
        {
          "name": "p_226513_",
          "type": "RandomSource",
          "annotations": []
        },
        {
          "name": "p_226514_",
          "type": "BoundingBox",
          "annotations": []
        },
        {
          "name": "p_226515_",
          "type": "BlockPos",
          "annotations": []
        },
        {
          "name": "p_226516_",
          "type": "boolean",
          "annotations": []
        }
      ],
      "description": "",
      "deprecated": false
    },
    {
      "name": "move",
      "modifiers": [
        "public"
      ],
      "return_type": "void",
      "parameters": [
        {
          "name": "p_72616_",
          "type": "int",
          "annotations": []
        },
        {
          "name": "p_72617_",
          "type": "int",
          "annotations": []
        },
        {
          "name": "p_72618_",
          "type": "int",
          "annotations": []
        }
      ],
      "description": "",
      "deprecated": false
    },
    {
      "name": "getRotation",
      "modifiers": [
        "public"
      ],
      "return_type": "Rotation",
      "parameters": [],
      "description": "",
      "deprecated": false
    },
    {
      "name": "toString",
      "modifiers": [
        "public"
      ],
      "return_type": "String",
      "parameters": [],
      "description": "",
      "deprecated": false
    },
    {
      "name": "getElement",
      "modifiers": [
        "public"
      ],
      "return_type": "StructurePoolElement",
      "parameters": [],
      "description": "",
      "deprecated": false
    },
    {
      "name": "getPosition",
      "modifiers": [
        "public"
      ],
      "return_type": "BlockPos",
      "parameters": [],
      "description": "",
      "deprecated": false
    },
    {
      "name": "getGroundLevelDelta",
      "modifiers": [
        "public"
      ],
      "return_type": "int",
      "parameters": [],
      "description": "",
      "deprecated": false
    },
    {
      "name": "addJunction",
      "modifiers": [
        "public"
      ],
      "return_type": "void",
      "parameters": [
        {
          "name": "p_209917_",
          "type": "JigsawJunction",
          "annotations": []
        }
      ],
      "description": "",
      "deprecated": false
    },
    {
      "name": "getJunctions",
      "modifiers": [
        "public"
      ],
      "return_type": "List < JigsawJunction >",
      "parameters": [],
      "description": "",
      "deprecated": false
    }
  ],
  "enum_constants": [],
  "since": null,
  "deprecated": false,
  "source_file": "Frameworks/1.19.4/net/minecraft/world/level/levelgen/structure/PoolElementStructurePiece.html"
}