{
  "type": "class",
  "name": "PlaySoundSourceEvent",
  "qualified_name": "net.minecraftforge.client.event.sound.PlaySoundSourceEvent",
  "package": "net.minecraftforge.client.event.sound",
  "modifiers": [
    "public",
    "class"
  ],
  "annotations": [],
  "description": "Fired when a non-streaming sound is being played. A non-streaming sound is loaded fully into memory in a buffer before being played, and used for most sounds of short length such as sound effects for clicking buttons. This event is not cancellable, and does not have a result. This event is fired on the main Forge event bus , only on the logical client .",
  "inheritance": {
    "extends": null,
    "implements": [],
    "inheritance_tree": [
      "java.lang.Object",
      "net.minecraftforge.client.event.sound.SoundEvent",
      "net.minecraftforge.client.event.sound.SoundEvent.SoundSourceEvent"
    ]
  },
  "nested_classes": [],
  "fields": [],
  "constructors": [
    {
      "name": "PlaySoundSourceEvent",
      "modifiers": [
        "public"
      ],
      "parameters": [
        {
          "name": "engine",
          "type": "SoundEngine",
          "annotations": []
        },
        {
          "name": "sound",
          "type": "SoundInstance",
          "annotations": []
        },
        {
          "name": "channel",
          "type": "Channel",
          "annotations": []
        }
      ],
      "description": "",
      "deprecated": false
    }
  ],
  "methods": [],
  "enum_constants": [],
  "since": null,
  "deprecated": false,
  "source_file": "Frameworks/1.20.2/net/minecraftforge/client/event/sound/PlaySoundSourceEvent.html"
}