{
  "type": "class",
  "name": "<T>>",
  "qualified_name": "net.minecraft.commands.execution.tasks.<T>>",
  "package": "net.minecraft.commands.execution.tasks",
  "modifiers": [
    "public",
    "static",
    "class"
  ],
  "annotations": [],
  "description": "",
  "inheritance": {
    "extends": null,
    "implements": [],
    "inheritance_tree": [
      "java.lang.Object",
      "net.minecraft.commands.execution.tasks.BuildContexts"
    ]
  },
  "nested_classes": [],
  "fields": [
    {
      "name": "modifiers",
      "modifiers": [
        "private",
        "final"
      ],
      "type": "ChainModifiers",
      "description": "",
      "deprecated": false
    },
    {
      "name": "originalSource",
      "modifiers": [
        "private",
        "final"
      ],
      "type": "T extends ExecutionCommandSource < T >",
      "description": "",
      "deprecated": false
    },
    {
      "name": "sources",
      "modifiers": [
        "private",
        "final"
      ],
      "type": "List < T extends ExecutionCommandSource < T >>",
      "description": "",
      "deprecated": false
    }
  ],
  "constructors": [
    {
      "name": "Continuation",
      "modifiers": [
        "public"
      ],
      "parameters": [
        {
          "name": "p_312336_",
          "type": "String",
          "annotations": []
        },
        {
          "name": "p_312118_",
          "type": "com.mojang.brigadier.context.ContextChain< T >",
          "annotations": []
        },
        {
          "name": "p_311446_",
          "type": "ChainModifiers",
          "annotations": []
        },
        {
          "name": "p_312390_",
          "type": "T",
          "annotations": []
        },
        {
          "name": "p_311252_",
          "type": "List < T >",
          "annotations": []
        }
      ],
      "description": "",
      "deprecated": false
    }
  ],
  "methods": [
    {
      "name": "execute",
      "modifiers": [
        "public"
      ],
      "return_type": "void",
      "parameters": [
        {
          "name": "p_310784_",
          "type": "ExecutionContext < T >",
          "annotations": []
        },
        {
          "name": "p_310508_",
          "type": "Frame",
          "annotations": []
        }
      ],
      "description": "",
      "deprecated": false
    }
  ],
  "enum_constants": [],
  "since": null,
  "deprecated": false,
  "source_file": "Frameworks/1.20.4/net/minecraft/commands/execution/tasks/BuildContexts.Continuation.html"
}