{
  "type": "class",
  "name": "MainMenuScreen",
  "qualified_name": "net.minecraft.client.gui.screen.MainMenuScreen",
  "package": "net.minecraft.client.gui.screen",
  "modifiers": [
    "public",
    "class"
  ],
  "annotations": [],
  "description": "",
  "inheritance": {
    "extends": null,
    "implements": [],
    "inheritance_tree": [
      "java.lang.Object",
      "net.minecraft.client.gui.AbstractGui",
      "net.minecraft.client.gui.FocusableGui",
      "net.minecraft.client.gui.screen.Screen"
    ]
  },
  "nested_classes": [],
  "fields": [
    {
      "name": "LOGGER",
      "modifiers": [
        "private",
        "static",
        "final"
      ],
      "type": "org.apache.logging.log4j.Logger",
      "description": "",
      "deprecated": false
    },
    {
      "name": "CUBE_MAP",
      "modifiers": [
        "public",
        "static",
        "final"
      ],
      "type": "RenderSkyboxCube",
      "description": "",
      "deprecated": false
    },
    {
      "name": "PANORAMA_OVERLAY",
      "modifiers": [
        "private",
        "static",
        "final"
      ],
      "type": "ResourceLocation",
      "description": "",
      "deprecated": false
    },
    {
      "name": "ACCESSIBILITY_TEXTURE",
      "modifiers": [
        "private",
        "static",
        "final"
      ],
      "type": "ResourceLocation",
      "description": "",
      "deprecated": false
    },
    {
      "name": "minceraftEasterEgg",
      "modifiers": [
        "private",
        "final"
      ],
      "type": "boolean",
      "description": "",
      "deprecated": false
    },
    {
      "name": "splash",
      "modifiers": [
        "private"
      ],
      "type": "String",
      "description": "",
      "deprecated": false
    },
    {
      "name": "resetDemoButton",
      "modifiers": [
        "private"
      ],
      "type": "Button",
      "description": "",
      "deprecated": false
    },
    {
      "name": "MINECRAFT_LOGO",
      "modifiers": [
        "private",
        "static",
        "final"
      ],
      "type": "ResourceLocation",
      "description": "",
      "deprecated": false
    },
    {
      "name": "MINECRAFT_EDITION",
      "modifiers": [
        "private",
        "static",
        "final"
      ],
      "type": "ResourceLocation",
      "description": "",
      "deprecated": false
    },
    {
      "name": "realmsNotificationsInitialized",
      "modifiers": [
        "private"
      ],
      "type": "boolean",
      "description": "",
      "deprecated": false
    },
    {
      "name": "realmsNotificationsScreen",
      "modifiers": [
        "private"
      ],
      "type": "Screen",
      "description": "",
      "deprecated": false
    },
    {
      "name": "copyrightWidth",
      "modifiers": [
        "private"
      ],
      "type": "int",
      "description": "",
      "deprecated": false
    },
    {
      "name": "copyrightX",
      "modifiers": [
        "private"
      ],
      "type": "int",
      "description": "",
      "deprecated": false
    },
    {
      "name": "panorama",
      "modifiers": [
        "private",
        "final"
      ],
      "type": "RenderSkybox",
      "description": "",
      "deprecated": false
    },
    {
      "name": "fading",
      "modifiers": [
        "private",
        "final"
      ],
      "type": "boolean",
      "description": "",
      "deprecated": false
    },
    {
      "name": "fadeInStart",
      "modifiers": [
        "private"
      ],
      "type": "long",
      "description": "",
      "deprecated": false
    },
    {
      "name": "modUpdateNotification",
      "modifiers": [
        "private"
      ],
      "type": "NotificationModUpdateScreen",
      "description": "",
      "deprecated": false
    }
  ],
  "constructors": [
    {
      "name": "MainMenuScreen",
      "modifiers": [
        "public"
      ],
      "parameters": [],
      "description": "",
      "deprecated": false
    },
    {
      "name": "MainMenuScreen",
      "modifiers": [
        "public"
      ],
      "parameters": [
        {
          "name": "p_i51107_1_",
          "type": "boolean",
          "annotations": []
        }
      ],
      "description": "",
      "deprecated": false
    }
  ],
  "methods": [
    {
      "name": "realmsNotificationsEnabled",
      "modifiers": [
        "private"
      ],
      "return_type": "boolean",
      "parameters": [],
      "description": "",
      "deprecated": false
    },
    {
      "name": "tick",
      "modifiers": [
        "public"
      ],
      "return_type": "void",
      "parameters": [],
      "description": "",
      "deprecated": false
    },
    {
      "name": "preloadResources",
      "modifiers": [
        "public",
        "static"
      ],
      "return_type": "CompletableFuture < Void >",
      "parameters": [
        {
          "name": "p_213097_0_",
          "type": "TextureManager",
          "annotations": []
        },
        {
          "name": "p_213097_1_",
          "type": "Executor",
          "annotations": []
        }
      ],
      "description": "",
      "deprecated": false
    },
    {
      "name": "isPauseScreen",
      "modifiers": [
        "public"
      ],
      "return_type": "boolean",
      "parameters": [],
      "description": "",
      "deprecated": false
    },
    {
      "name": "shouldCloseOnEsc",
      "modifiers": [
        "public"
      ],
      "return_type": "boolean",
      "parameters": [],
      "description": "",
      "deprecated": false
    },
    {
      "name": "init",
      "modifiers": [
        "protected"
      ],
      "return_type": "void",
      "parameters": [],
      "description": "",
      "deprecated": false
    },
    {
      "name": "createNormalMenuOptions",
      "modifiers": [
        "private"
      ],
      "return_type": "void",
      "parameters": [
        {
          "name": "p_73969_1_",
          "type": "int",
          "annotations": []
        },
        {
          "name": "p_73969_2_",
          "type": "int",
          "annotations": []
        }
      ],
      "description": "",
      "deprecated": false
    },
    {
      "name": "createDemoMenuOptions",
      "modifiers": [
        "private"
      ],
      "return_type": "void",
      "parameters": [
        {
          "name": "p_73972_1_",
          "type": "int",
          "annotations": []
        },
        {
          "name": "p_73972_2_",
          "type": "int",
          "annotations": []
        }
      ],
      "description": "",
      "deprecated": false
    },
    {
      "name": "checkDemoWorldPresence",
      "modifiers": [
        "private"
      ],
      "return_type": "boolean",
      "parameters": [],
      "description": "",
      "deprecated": false
    },
    {
      "name": "realmsButtonClicked",
      "modifiers": [
        "private"
      ],
      "return_type": "void",
      "parameters": [],
      "description": "",
      "deprecated": false
    },
    {
      "name": "render",
      "modifiers": [
        "public"
      ],
      "return_type": "void",
      "parameters": [
        {
          "name": "p_230430_1_",
          "type": "MatrixStack",
          "annotations": []
        },
        {
          "name": "p_230430_2_",
          "type": "int",
          "annotations": []
        },
        {
          "name": "p_230430_3_",
          "type": "int",
          "annotations": []
        },
        {
          "name": "p_230430_4_",
          "type": "float",
          "annotations": []
        }
      ],
      "description": "",
      "deprecated": false
    },
    {
      "name": "mouseClicked",
      "modifiers": [
        "public"
      ],
      "return_type": "boolean",
      "parameters": [
        {
          "name": "p_231044_1_",
          "type": "double",
          "annotations": []
        },
        {
          "name": "p_231044_3_",
          "type": "double",
          "annotations": []
        },
        {
          "name": "p_231044_5_",
          "type": "int",
          "annotations": []
        }
      ],
      "description": "",
      "deprecated": false
    },
    {
      "name": "removed",
      "modifiers": [
        "public"
      ],
      "return_type": "void",
      "parameters": [],
      "description": "",
      "deprecated": false
    },
    {
      "name": "confirmDemo",
      "modifiers": [
        "private"
      ],
      "return_type": "void",
      "parameters": [
        {
          "name": "p_213087_1_",
          "type": "boolean",
          "annotations": []
        }
      ],
      "description": "",
      "deprecated": false
    }
  ],
  "enum_constants": [],
  "since": null,
  "deprecated": false,
  "source_file": "Frameworks/1.16.5/net/minecraft/client/gui/screen/MainMenuScreen.html"
}