{
  "type": "class",
  "name": "ChunkBedBlockEntityInjecterFix",
  "qualified_name": "net.minecraft.util.datafix.fixes.ChunkBedBlockEntityInjecterFix",
  "package": "net.minecraft.util.datafix.fixes",
  "modifiers": [
    "public",
    "class"
  ],
  "annotations": [],
  "description": "",
  "inheritance": {
    "extends": null,
    "implements": [],
    "inheritance_tree": [
      "java.lang.Object"
    ]
  },
  "nested_classes": [],
  "fields": [],
  "constructors": [
    {
      "name": "ChunkBedBlockEntityInjecterFix",
      "modifiers": [
        "public"
      ],
      "parameters": [
        {
          "name": "p_184825_",
          "type": "com.mojang.datafixers.schemas.Schema",
          "annotations": []
        },
        {
          "name": "p_184826_",
          "type": "boolean",
          "annotations": []
        }
      ],
      "description": "",
      "deprecated": false
    }
  ],
  "methods": [
    {
      "name": "makeRule",
      "modifiers": [
        "public"
      ],
      "return_type": "com.mojang.datafixers.TypeRewriteRule",
      "parameters": [],
      "description": "",
      "deprecated": false
    },
    {
      "name": "cap",
      "modifiers": [
        "private"
      ],
      "return_type": "com.mojang.datafixers.TypeRewriteRule",
      "parameters": [
        {
          "name": "p_184834_",
          "type": "com.mojang.datafixers.types.Type<?>",
          "annotations": []
        },
        {
          "name": "p_184835_",
          "type": "com.mojang.datafixers.types.templates.List.ListType<TE>",
          "annotations": []
        }
      ],
      "description": "",
      "deprecated": false
    }
  ],
  "enum_constants": [],
  "since": null,
  "deprecated": false,
  "source_file": "Frameworks/1.20.1/net/minecraft/util/datafix/fixes/ChunkBedBlockEntityInjecterFix.html"
}