{
  "type": "class",
  "name": "ItemEntity",
  "qualified_name": "net.minecraft.entity.item.ItemEntity",
  "package": "net.minecraft.entity.item",
  "modifiers": [
    "public",
    "class"
  ],
  "annotations": [],
  "description": "",
  "inheritance": {
    "extends": null,
    "implements": [],
    "inheritance_tree": [
      "java.lang.Object",
      "net.minecraftforge.common.capabilities.CapabilityProvider",
      "Entity",
      "net.minecraft.entity.Entity"
    ]
  },
  "nested_classes": [],
  "fields": [
    {
      "name": "DATA_ITEM",
      "modifiers": [
        "private",
        "static",
        "final"
      ],
      "type": "DataParameter < ItemStack >",
      "description": "",
      "deprecated": false
    },
    {
      "name": "age",
      "modifiers": [
        "private"
      ],
      "type": "int",
      "description": "",
      "deprecated": false
    },
    {
      "name": "pickupDelay",
      "modifiers": [
        "private"
      ],
      "type": "int",
      "description": "",
      "deprecated": false
    },
    {
      "name": "health",
      "modifiers": [
        "private"
      ],
      "type": "int",
      "description": "",
      "deprecated": false
    },
    {
      "name": "thrower",
      "modifiers": [
        "private"
      ],
      "type": "UUID",
      "description": "",
      "deprecated": false
    },
    {
      "name": "owner",
      "modifiers": [
        "private"
      ],
      "type": "UUID",
      "description": "",
      "deprecated": false
    },
    {
      "name": "bobOffs",
      "modifiers": [
        "public",
        "final"
      ],
      "type": "float",
      "description": "",
      "deprecated": false
    },
    {
      "name": "lifespan",
      "modifiers": [
        "public"
      ],
      "type": "int",
      "description": "The maximum age of this EntityItem. The item is expired once this is reached.",
      "deprecated": false
    }
  ],
  "constructors": [
    {
      "name": "ItemEntity",
      "modifiers": [
        "public"
      ],
      "parameters": [
        {
          "name": "p_i50217_1_",
          "type": "EntityType <? extends ItemEntity >",
          "annotations": []
        },
        {
          "name": "p_i50217_2_",
          "type": "World",
          "annotations": []
        }
      ],
      "description": "",
      "deprecated": false
    },
    {
      "name": "ItemEntity",
      "modifiers": [
        "public"
      ],
      "parameters": [
        {
          "name": "p_i1709_1_",
          "type": "World",
          "annotations": []
        },
        {
          "name": "p_i1709_2_",
          "type": "double",
          "annotations": []
        },
        {
          "name": "p_i1709_4_",
          "type": "double",
          "annotations": []
        },
        {
          "name": "p_i1709_6_",
          "type": "double",
          "annotations": []
        }
      ],
      "description": "",
      "deprecated": false
    },
    {
      "name": "ItemEntity",
      "modifiers": [
        "public"
      ],
      "parameters": [
        {
          "name": "p_i1710_1_",
          "type": "World",
          "annotations": []
        },
        {
          "name": "p_i1710_2_",
          "type": "double",
          "annotations": []
        },
        {
          "name": "p_i1710_4_",
          "type": "double",
          "annotations": []
        },
        {
          "name": "p_i1710_6_",
          "type": "double",
          "annotations": []
        },
        {
          "name": "p_i1710_8_",
          "type": "ItemStack",
          "annotations": []
        }
      ],
      "description": "",
      "deprecated": false
    },
    {
      "name": "ItemEntity",
      "modifiers": [
        "private"
      ],
      "parameters": [
        {
          "name": "p_i231561_1_",
          "type": "ItemEntity",
          "annotations": []
        }
      ],
      "description": "",
      "deprecated": false
    }
  ],
  "methods": [
    {
      "name": "isMovementNoisy",
      "modifiers": [
        "protected"
      ],
      "return_type": "boolean",
      "parameters": [],
      "description": "",
      "deprecated": false
    },
    {
      "name": "defineSynchedData",
      "modifiers": [
        "protected"
      ],
      "return_type": "void",
      "parameters": [],
      "description": "",
      "deprecated": false
    },
    {
      "name": "tick",
      "modifiers": [
        "public"
      ],
      "return_type": "void",
      "parameters": [],
      "description": "",
      "deprecated": false
    },
    {
      "name": "setUnderwaterMovement",
      "modifiers": [
        "private"
      ],
      "return_type": "void",
      "parameters": [],
      "description": "",
      "deprecated": false
    },
    {
      "name": "setUnderLavaMovement",
      "modifiers": [
        "private"
      ],
      "return_type": "void",
      "parameters": [],
      "description": "",
      "deprecated": false
    },
    {
      "name": "mergeWithNeighbours",
      "modifiers": [
        "private"
      ],
      "return_type": "void",
      "parameters": [],
      "description": "",
      "deprecated": false
    },
    {
      "name": "isMergable",
      "modifiers": [
        "private"
      ],
      "return_type": "boolean",
      "parameters": [],
      "description": "",
      "deprecated": false
    },
    {
      "name": "tryToMerge",
      "modifiers": [
        "private"
      ],
      "return_type": "void",
      "parameters": [
        {
          "name": "p_226530_1_",
          "type": "ItemEntity",
          "annotations": []
        }
      ],
      "description": "",
      "deprecated": false
    },
    {
      "name": "areMergable",
      "modifiers": [
        "public",
        "static"
      ],
      "return_type": "boolean",
      "parameters": [
        {
          "name": "p_226532_0_",
          "type": "ItemStack",
          "annotations": []
        },
        {
          "name": "p_226532_1_",
          "type": "ItemStack",
          "annotations": []
        }
      ],
      "description": "",
      "deprecated": false
    },
    {
      "name": "merge",
      "modifiers": [
        "public",
        "static"
      ],
      "return_type": "ItemStack",
      "parameters": [
        {
          "name": "p_226533_0_",
          "type": "ItemStack",
          "annotations": []
        },
        {
          "name": "p_226533_1_",
          "type": "ItemStack",
          "annotations": []
        },
        {
          "name": "p_226533_2_",
          "type": "int",
          "annotations": []
        }
      ],
      "description": "",
      "deprecated": false
    },
    {
      "name": "merge",
      "modifiers": [
        "private",
        "static"
      ],
      "return_type": "void",
      "parameters": [
        {
          "name": "p_226531_0_",
          "type": "ItemEntity",
          "annotations": []
        },
        {
          "name": "p_226531_1_",
          "type": "ItemStack",
          "annotations": []
        },
        {
          "name": "p_226531_2_",
          "type": "ItemStack",
          "annotations": []
        }
      ],
      "description": "",
      "deprecated": false
    },
    {
      "name": "merge",
      "modifiers": [
        "private",
        "static"
      ],
      "return_type": "void",
      "parameters": [
        {
          "name": "p_213858_0_",
          "type": "ItemEntity",
          "annotations": []
        },
        {
          "name": "p_213858_1_",
          "type": "ItemStack",
          "annotations": []
        },
        {
          "name": "p_213858_2_",
          "type": "ItemEntity",
          "annotations": []
        },
        {
          "name": "p_213858_3_",
          "type": "ItemStack",
          "annotations": []
        }
      ],
      "description": "",
      "deprecated": false
    },
    {
      "name": "fireImmune",
      "modifiers": [
        "public"
      ],
      "return_type": "boolean",
      "parameters": [],
      "description": "",
      "deprecated": false
    },
    {
      "name": "hurt",
      "modifiers": [
        "public"
      ],
      "return_type": "boolean",
      "parameters": [
        {
          "name": "p_70097_1_",
          "type": "DamageSource",
          "annotations": []
        },
        {
          "name": "p_70097_2_",
          "type": "float",
          "annotations": []
        }
      ],
      "description": "",
      "deprecated": false
    },
    {
      "name": "addAdditionalSaveData",
      "modifiers": [
        "public"
      ],
      "return_type": "void",
      "parameters": [
        {
          "name": "p_213281_1_",
          "type": "CompoundNBT",
          "annotations": []
        }
      ],
      "description": "",
      "deprecated": false
    },
    {
      "name": "readAdditionalSaveData",
      "modifiers": [
        "public"
      ],
      "return_type": "void",
      "parameters": [
        {
          "name": "p_70037_1_",
          "type": "CompoundNBT",
          "annotations": []
        }
      ],
      "description": "",
      "deprecated": false
    },
    {
      "name": "playerTouch",
      "modifiers": [
        "public"
      ],
      "return_type": "void",
      "parameters": [
        {
          "name": "p_70100_1_",
          "type": "PlayerEntity",
          "annotations": []
        }
      ],
      "description": "",
      "deprecated": false
    },
    {
      "name": "getName",
      "modifiers": [
        "public"
      ],
      "return_type": "ITextComponent",
      "parameters": [],
      "description": "",
      "deprecated": false
    },
    {
      "name": "isAttackable",
      "modifiers": [
        "public"
      ],
      "return_type": "boolean",
      "parameters": [],
      "description": "",
      "deprecated": false
    },
    {
      "name": "changeDimension",
      "modifiers": [
        "public"
      ],
      "return_type": "Entity",
      "parameters": [
        {
          "name": "p_241206_1_",
          "type": "ServerWorld",
          "annotations": []
        },
        {
          "name": "teleporter",
          "type": "ITeleporter",
          "annotations": []
        }
      ],
      "description": "",
      "deprecated": false
    },
    {
      "name": "getItem",
      "modifiers": [
        "public"
      ],
      "return_type": "ItemStack",
      "parameters": [],
      "description": "",
      "deprecated": false
    },
    {
      "name": "setItem",
      "modifiers": [
        "public"
      ],
      "return_type": "void",
      "parameters": [
        {
          "name": "p_92058_1_",
          "type": "ItemStack",
          "annotations": []
        }
      ],
      "description": "",
      "deprecated": false
    },
    {
      "name": "onSyncedDataUpdated",
      "modifiers": [
        "public"
      ],
      "return_type": "void",
      "parameters": [
        {
          "name": "p_184206_1_",
          "type": "DataParameter <?>",
          "annotations": []
        }
      ],
      "description": "",
      "deprecated": false
    },
    {
      "name": "getOwner",
      "modifiers": [
        "public"
      ],
      "return_type": "UUID",
      "parameters": [],
      "description": "",
      "deprecated": false
    },
    {
      "name": "setOwner",
      "modifiers": [
        "public"
      ],
      "return_type": "void",
      "parameters": [
        {
          "name": "p_200217_1_",
          "type": "UUID",
          "annotations": [
            "Nullable"
          ]
        }
      ],
      "description": "",
      "deprecated": false
    },
    {
      "name": "getThrower",
      "modifiers": [
        "public"
      ],
      "return_type": "UUID",
      "parameters": [],
      "description": "",
      "deprecated": false
    },
    {
      "name": "setThrower",
      "modifiers": [
        "public"
      ],
      "return_type": "void",
      "parameters": [
        {
          "name": "p_200216_1_",
          "type": "UUID",
          "annotations": [
            "Nullable"
          ]
        }
      ],
      "description": "",
      "deprecated": false
    },
    {
      "name": "getAge",
      "modifiers": [
        "public"
      ],
      "return_type": "int",
      "parameters": [],
      "description": "",
      "deprecated": false
    },
    {
      "name": "setDefaultPickUpDelay",
      "modifiers": [
        "public"
      ],
      "return_type": "void",
      "parameters": [],
      "description": "",
      "deprecated": false
    },
    {
      "name": "setNoPickUpDelay",
      "modifiers": [
        "public"
      ],
      "return_type": "void",
      "parameters": [],
      "description": "",
      "deprecated": false
    },
    {
      "name": "setNeverPickUp",
      "modifiers": [
        "public"
      ],
      "return_type": "void",
      "parameters": [],
      "description": "",
      "deprecated": false
    },
    {
      "name": "setPickUpDelay",
      "modifiers": [
        "public"
      ],
      "return_type": "void",
      "parameters": [
        {
          "name": "p_174867_1_",
          "type": "int",
          "annotations": []
        }
      ],
      "description": "",
      "deprecated": false
    },
    {
      "name": "hasPickUpDelay",
      "modifiers": [
        "public"
      ],
      "return_type": "boolean",
      "parameters": [],
      "description": "",
      "deprecated": false
    },
    {
      "name": "setExtendedLifetime",
      "modifiers": [
        "public"
      ],
      "return_type": "void",
      "parameters": [],
      "description": "",
      "deprecated": false
    },
    {
      "name": "makeFakeItem",
      "modifiers": [
        "public"
      ],
      "return_type": "void",
      "parameters": [],
      "description": "",
      "deprecated": false
    },
    {
      "name": "getSpin",
      "modifiers": [
        "public"
      ],
      "return_type": "float",
      "parameters": [
        {
          "name": "p_234272_1_",
          "type": "float",
          "annotations": []
        }
      ],
      "description": "",
      "deprecated": false
    },
    {
      "name": "getAddEntityPacket",
      "modifiers": [
        "public"
      ],
      "return_type": "IPacket <?>",
      "parameters": [],
      "description": "",
      "deprecated": false
    },
    {
      "name": "copy",
      "modifiers": [
        "public"
      ],
      "return_type": "ItemEntity",
      "parameters": [],
      "description": "",
      "deprecated": false
    }
  ],
  "enum_constants": [],
  "since": null,
  "deprecated": false,
  "source_file": "Frameworks/1.16.5/net/minecraft/entity/item/ItemEntity.html"
}