{
  "type": "class",
  "name": "Camera",
  "qualified_name": "net.minecraft.client.Camera",
  "package": "net.minecraft.client",
  "modifiers": [
    "public",
    "class"
  ],
  "annotations": [],
  "description": "",
  "inheritance": {
    "extends": null,
    "implements": [],
    "inheritance_tree": [
      "java.lang.Object"
    ]
  },
  "nested_classes": [],
  "fields": [
    {
      "name": "initialized",
      "modifiers": [
        "private"
      ],
      "type": "boolean",
      "description": "",
      "deprecated": false
    },
    {
      "name": "level",
      "modifiers": [
        "private"
      ],
      "type": "BlockGetter",
      "description": "",
      "deprecated": false
    },
    {
      "name": "entity",
      "modifiers": [
        "private"
      ],
      "type": "Entity",
      "description": "",
      "deprecated": false
    },
    {
      "name": "position",
      "modifiers": [
        "private"
      ],
      "type": "Vec3",
      "description": "",
      "deprecated": false
    },
    {
      "name": "blockPosition",
      "modifiers": [
        "private",
        "final"
      ],
      "type": "BlockPos.MutableBlockPos",
      "description": "",
      "deprecated": false
    },
    {
      "name": "forwards",
      "modifiers": [
        "private",
        "final"
      ],
      "type": "Vector3f",
      "description": "",
      "deprecated": false
    },
    {
      "name": "up",
      "modifiers": [
        "private",
        "final"
      ],
      "type": "Vector3f",
      "description": "",
      "deprecated": false
    },
    {
      "name": "left",
      "modifiers": [
        "private",
        "final"
      ],
      "type": "Vector3f",
      "description": "",
      "deprecated": false
    },
    {
      "name": "xRot",
      "modifiers": [
        "private"
      ],
      "type": "float",
      "description": "",
      "deprecated": false
    },
    {
      "name": "yRot",
      "modifiers": [
        "private"
      ],
      "type": "float",
      "description": "",
      "deprecated": false
    },
    {
      "name": "rotation",
      "modifiers": [
        "private",
        "final"
      ],
      "type": "Quaternion",
      "description": "",
      "deprecated": false
    },
    {
      "name": "detached",
      "modifiers": [
        "private"
      ],
      "type": "boolean",
      "description": "",
      "deprecated": false
    },
    {
      "name": "eyeHeight",
      "modifiers": [
        "private"
      ],
      "type": "float",
      "description": "",
      "deprecated": false
    },
    {
      "name": "eyeHeightOld",
      "modifiers": [
        "private"
      ],
      "type": "float",
      "description": "",
      "deprecated": false
    },
    {
      "name": "FOG_DISTANCE_SCALE",
      "modifiers": [
        "public",
        "static",
        "final"
      ],
      "type": "float",
      "description": "",
      "deprecated": false
    }
  ],
  "constructors": [
    {
      "name": "Camera",
      "modifiers": [
        "public"
      ],
      "parameters": [],
      "description": "",
      "deprecated": false
    }
  ],
  "methods": [
    {
      "name": "setup",
      "modifiers": [
        "public"
      ],
      "return_type": "void",
      "parameters": [
        {
          "name": "p_90576_",
          "type": "BlockGetter",
          "annotations": []
        },
        {
          "name": "p_90577_",
          "type": "Entity",
          "annotations": []
        },
        {
          "name": "p_90578_",
          "type": "boolean",
          "annotations": []
        },
        {
          "name": "p_90579_",
          "type": "boolean",
          "annotations": []
        },
        {
          "name": "p_90580_",
          "type": "float",
          "annotations": []
        }
      ],
      "description": "",
      "deprecated": false
    },
    {
      "name": "tick",
      "modifiers": [
        "public"
      ],
      "return_type": "void",
      "parameters": [],
      "description": "",
      "deprecated": false
    },
    {
      "name": "getMaxZoom",
      "modifiers": [
        "private"
      ],
      "return_type": "double",
      "parameters": [
        {
          "name": "p_90567_",
          "type": "double",
          "annotations": []
        }
      ],
      "description": "",
      "deprecated": false
    },
    {
      "name": "move",
      "modifiers": [
        "protected"
      ],
      "return_type": "void",
      "parameters": [
        {
          "name": "p_90569_",
          "type": "double",
          "annotations": []
        },
        {
          "name": "p_90570_",
          "type": "double",
          "annotations": []
        },
        {
          "name": "p_90571_",
          "type": "double",
          "annotations": []
        }
      ],
      "description": "",
      "deprecated": false
    },
    {
      "name": "setRotation",
      "modifiers": [
        "protected"
      ],
      "return_type": "void",
      "parameters": [
        {
          "name": "p_90573_",
          "type": "float",
          "annotations": []
        },
        {
          "name": "p_90574_",
          "type": "float",
          "annotations": []
        }
      ],
      "description": "",
      "deprecated": false
    },
    {
      "name": "setPosition",
      "modifiers": [
        "protected"
      ],
      "return_type": "void",
      "parameters": [
        {
          "name": "p_90585_",
          "type": "double",
          "annotations": []
        },
        {
          "name": "p_90586_",
          "type": "double",
          "annotations": []
        },
        {
          "name": "p_90587_",
          "type": "double",
          "annotations": []
        }
      ],
      "description": "",
      "deprecated": false
    },
    {
      "name": "setPosition",
      "modifiers": [
        "protected"
      ],
      "return_type": "void",
      "parameters": [
        {
          "name": "p_90582_",
          "type": "Vec3",
          "annotations": []
        }
      ],
      "description": "",
      "deprecated": false
    },
    {
      "name": "getPosition",
      "modifiers": [
        "public"
      ],
      "return_type": "Vec3",
      "parameters": [],
      "description": "",
      "deprecated": false
    },
    {
      "name": "getBlockPosition",
      "modifiers": [
        "public"
      ],
      "return_type": "BlockPos",
      "parameters": [],
      "description": "",
      "deprecated": false
    },
    {
      "name": "getXRot",
      "modifiers": [
        "public"
      ],
      "return_type": "float",
      "parameters": [],
      "description": "",
      "deprecated": false
    },
    {
      "name": "getYRot",
      "modifiers": [
        "public"
      ],
      "return_type": "float",
      "parameters": [],
      "description": "",
      "deprecated": false
    },
    {
      "name": "rotation",
      "modifiers": [
        "public"
      ],
      "return_type": "Quaternion",
      "parameters": [],
      "description": "",
      "deprecated": false
    },
    {
      "name": "getEntity",
      "modifiers": [
        "public"
      ],
      "return_type": "Entity",
      "parameters": [],
      "description": "",
      "deprecated": false
    },
    {
      "name": "isInitialized",
      "modifiers": [
        "public"
      ],
      "return_type": "boolean",
      "parameters": [],
      "description": "",
      "deprecated": false
    },
    {
      "name": "isDetached",
      "modifiers": [
        "public"
      ],
      "return_type": "boolean",
      "parameters": [],
      "description": "",
      "deprecated": false
    },
    {
      "name": "getNearPlane",
      "modifiers": [
        "public"
      ],
      "return_type": "Camera.NearPlane",
      "parameters": [],
      "description": "",
      "deprecated": false
    },
    {
      "name": "getFluidInCamera",
      "modifiers": [
        "public"
      ],
      "return_type": "FogType",
      "parameters": [],
      "description": "",
      "deprecated": false
    },
    {
      "name": "getLookVector",
      "modifiers": [
        "public",
        "final"
      ],
      "return_type": "Vector3f",
      "parameters": [],
      "description": "",
      "deprecated": false
    },
    {
      "name": "getUpVector",
      "modifiers": [
        "public",
        "final"
      ],
      "return_type": "Vector3f",
      "parameters": [],
      "description": "",
      "deprecated": false
    },
    {
      "name": "getLeftVector",
      "modifiers": [
        "public",
        "final"
      ],
      "return_type": "Vector3f",
      "parameters": [],
      "description": "",
      "deprecated": false
    },
    {
      "name": "reset",
      "modifiers": [
        "public"
      ],
      "return_type": "void",
      "parameters": [],
      "description": "",
      "deprecated": false
    },
    {
      "name": "setAnglesInternal",
      "modifiers": [
        "public"
      ],
      "return_type": "void",
      "parameters": [
        {
          "name": "yaw",
          "type": "float",
          "annotations": []
        },
        {
          "name": "pitch",
          "type": "float",
          "annotations": []
        }
      ],
      "description": "",
      "deprecated": false
    },
    {
      "name": "getBlockAtCamera",
      "modifiers": [
        "public"
      ],
      "return_type": "BlockState",
      "parameters": [],
      "description": "",
      "deprecated": false
    }
  ],
  "enum_constants": [],
  "since": null,
  "deprecated": false,
  "source_file": "Frameworks/1.18.2/net/minecraft/client/Camera.html"
}